{
  "photos": {
    "animals": [
      {
        "id": "j93TpS17",
        "folder": "animals/3840/",
        "title": "A952-3840p-75",
        "description": "",
        "width": 3840,
        "height": 2560,
        "src": "https://media.publit.io/file/animals/3840/A952-3840p-75.jpg"
      },
      {
        "id": "NXkZ6jrn",
        "folder": "animals/3840/",
        "title": "A837-3840p-75",
        "description": "",
        "width": 3840,
        "height": 2880,
        "src": "https://media.publit.io/file/animals/3840/A837-3840p-75.jpg"
      },
      {
        "id": "o1P01i1L",
        "folder": "animals/3840/",
        "title": "A731-3840p-75",
        "description": "",
        "width": 3840,
        "height": 2880,
        "src": "https://media.publit.io/file/animals/3840/A731-3840p-75.jpg"
      },
      {
        "id": "u7Lrss7o",
        "folder": "animals/3840/",
        "title": "A711-3840p-75",
        "description": "",
        "width": 3840,
        "height": 2880,
        "src": "https://media.publit.io/file/animals/3840/A711-3840p-75.jpg"
      },
      {
        "id": "qJnnyNQu",
        "folder": "animals/3840/",
        "title": "A665-3840p-75",
        "description": "",
        "width": 3840,
        "height": 2880,
        "src": "https://media.publit.io/file/animals/3840/A665-3840p-75.jpg"
      },
      {
        "id": "RHJVmk3s",
        "folder": "animals/3840/",
        "title": "A652-3840p-75",
        "description": "",
        "width": 3840,
        "height": 2880,
        "src": "https://media.publit.io/file/animals/3840/A652-3840p-75.jpg"
      },
      {
        "id": "pBZAfiNp",
        "folder": "animals/3840/",
        "title": "A626-3840p-75",
        "description": "",
        "width": 2880,
        "height": 3840,
        "src": "https://media.publit.io/file/animals/3840/A626-3840p-75.jpg"
      },
      {
        "id": "bqR3xlD7",
        "folder": "animals/3840/",
        "title": "A585-3840p-75",
        "description": "",
        "width": 2880,
        "height": 3840,
        "src": "https://media.publit.io/file/animals/3840/A585-3840p-75.jpg"
      },
      {
        "id": "o7lDRplW",
        "folder": "animals/3840/",
        "title": "A536-3840p-75",
        "description": "",
        "width": 3840,
        "height": 2560,
        "src": "https://media.publit.io/file/animals/3840/A536-3840p-75.jpg"
      },
      {
        "id": "wnJP9qmf",
        "folder": "animals/3840/",
        "title": "A520-3840p-75",
        "description": "",
        "width": 3840,
        "height": 2880,
        "src": "https://media.publit.io/file/animals/3840/A520-3840p-75.jpg"
      },
      {
        "id": "aJ0QqLct",
        "folder": "animals/3840/",
        "title": "A505-3840p-75",
        "description": "",
        "width": 3840,
        "height": 2880,
        "src": "https://media.publit.io/file/animals/3840/A505-3840p-75.jpg"
      },
      {
        "id": "lJonfhB7",
        "folder": "animals/3840/",
        "title": "A386-3840p-75",
        "description": "",
        "width": 3840,
        "height": 2880,
        "src": "https://media.publit.io/file/animals/3840/A386-3840p-75.jpg"
      },
      {
        "id": "qeRaDdM5",
        "folder": "animals/3840/",
        "title": "A314-3840p-75",
        "description": "",
        "width": 3840,
        "height": 2560,
        "src": "https://media.publit.io/file/animals/3840/A314-3840p-75.jpg"
      },
      {
        "id": "z5ghu3yg",
        "folder": "animals/3840/",
        "title": "A307-3840p-75",
        "description": "",
        "width": 2557,
        "height": 3840,
        "src": "https://media.publit.io/file/animals/3840/A307-3840p-75.jpg"
      },
      {
        "id": "scq2XHvS",
        "folder": "animals/3840/",
        "title": "A197-3840p-75",
        "description": "",
        "width": 3840,
        "height": 2880,
        "src": "https://media.publit.io/file/animals/3840/A197-3840p-75.jpg"
      },
      {
        "id": "HSyMRW7i",
        "folder": "animals/3840/",
        "title": "A184-3840p-75",
        "description": "",
        "width": 3840,
        "height": 2560,
        "src": "https://media.publit.io/file/animals/3840/A184-3840p-75.jpg"
      },
      {
        "id": "Z2wkayMg",
        "folder": "animals/3840/",
        "title": "A133-3840p-75",
        "description": "",
        "width": 3840,
        "height": 2560,
        "src": "https://media.publit.io/file/animals/3840/A133-3840p-75.jpg"
      },
      {
        "id": "wLuBnHT6",
        "folder": "animals/3840/",
        "title": "A116-3840p-75",
        "description": "",
        "width": 3840,
        "height": 2560,
        "src": "https://media.publit.io/file/animals/3840/A116-3840p-75.jpg"
      },
      {
        "id": "hp2g4Wdd",
        "folder": "animals/3840/",
        "title": "A041-3840p-75",
        "description": "",
        "width": 2560,
        "height": 3840,
        "src": "https://media.publit.io/file/animals/3840/A041-3840p-75.jpg"
      },
      {
        "id": "RXl9XdyT",
        "folder": "animals/3840/",
        "title": "A038-3840p-75",
        "description": "",
        "width": 3840,
        "height": 2880,
        "src": "https://media.publit.io/file/animals/3840/A038-3840p-75.jpg"
      },
      {
        "id": "40T3mlvd",
        "folder": "animals/3840/",
        "title": "A020-3840p-75",
        "description": "",
        "width": 2800,
        "height": 3734,
        "src": "https://media.publit.io/file/animals/3840/A020-3840p-75.jpg"
      },
      {
        "id": "irMhg4jG",
        "folder": "animals/3840/",
        "title": "A019-3840p-75",
        "description": "",
        "width": 2880,
        "height": 3840,
        "src": "https://media.publit.io/file/animals/3840/A019-3840p-75.jpg"
      }
    ],
    "street": [
      {
        "id": "zPt3oHMy",
        "folder": "street/3840/",
        "title": "S936-3840p-75",
        "description": "",
        "width": 3840,
        "height": 2880,
        "src": "https://media.publit.io/file/street/3840/S936-3840p-75.jpg"
      },
      {
        "id": "9ibuajeN",
        "folder": "street/3840/",
        "title": "S856-3840p-75",
        "description": "",
        "width": 2560,
        "height": 3840,
        "src": "https://media.publit.io/file/street/3840/S856-3840p-75.jpg"
      },
      {
        "id": "invjgNyi",
        "folder": "street/3840/",
        "title": "S825-3840p-75",
        "description": "",
        "width": 2880,
        "height": 3840,
        "src": "https://media.publit.io/file/street/3840/S825-3840p-75.jpg"
      },
      {
        "id": "QTcpw5ba",
        "folder": "street/3840/",
        "title": "S782-3840p-75",
        "description": "",
        "width": 3840,
        "height": 2560,
        "src": "https://media.publit.io/file/street/3840/S782-3840p-75.jpg"
      },
      {
        "id": "blnL1z3D",
        "folder": "street/3840/",
        "title": "S779-3840p-75",
        "description": "",
        "width": 3840,
        "height": 2560,
        "src": "https://media.publit.io/file/street/3840/S779-3840p-75.jpg"
      },
      {
        "id": "l6tGjP26",
        "folder": "street/3840/",
        "title": "S778-3840p-75",
        "description": "",
        "width": 3840,
        "height": 2880,
        "src": "https://media.publit.io/file/street/3840/S778-3840p-75.jpg"
      },
      {
        "id": "Z4Rbkn1m",
        "folder": "street/3840/",
        "title": "S763-3840p-75",
        "description": "",
        "width": 3840,
        "height": 2880,
        "src": "https://media.publit.io/file/street/3840/S763-3840p-75.jpg"
      },
      {
        "id": "qtlV0TbV",
        "folder": "street/3840/",
        "title": "S756-3840p-75",
        "description": "",
        "width": 3840,
        "height": 2560,
        "src": "https://media.publit.io/file/street/3840/S756-3840p-75.jpg"
      },
      {
        "id": "cAzBzbbs",
        "folder": "street/3840/",
        "title": "S753-3840p-75",
        "description": "",
        "width": 3840,
        "height": 2880,
        "src": "https://media.publit.io/file/street/3840/S753-3840p-75.jpg"
      },
      {
        "id": "4006J42V",
        "folder": "street/3840/",
        "title": "S701-3840p-75",
        "description": "",
        "width": 3840,
        "height": 2560,
        "src": "https://media.publit.io/file/street/3840/S701-3840p-75.jpg"
      },
      {
        "id": "eiPWJmVW",
        "folder": "street/3840/",
        "title": "S593-3840p-75",
        "description": "",
        "width": 3840,
        "height": 2880,
        "src": "https://media.publit.io/file/street/3840/S593-3840p-75.jpg"
      },
      {
        "id": "1GsTaPXj",
        "folder": "street/3840/",
        "title": "S589-3840p-75",
        "description": "",
        "width": 2880,
        "height": 3840,
        "src": "https://media.publit.io/file/street/3840/S589-3840p-75.jpg"
      },
      {
        "id": "p2xXNJhS",
        "folder": "street/3840/",
        "title": "S588-3840p-75",
        "description": "",
        "width": 3840,
        "height": 2880,
        "src": "https://media.publit.io/file/street/3840/S588-3840p-75.jpg"
      },
      {
        "id": "dSgqgPuR",
        "folder": "street/3840/",
        "title": "S552-3840p-75",
        "description": "",
        "width": 3840,
        "height": 2560,
        "src": "https://media.publit.io/file/street/3840/S552-3840p-75.jpg"
      },
      {
        "id": "B541dHJe",
        "folder": "street/3840/",
        "title": "S543-3840p-75",
        "description": "",
        "width": 3840,
        "height": 2560,
        "src": "https://media.publit.io/file/street/3840/S543-3840p-75.jpg"
      },
      {
        "id": "39tszg8p",
        "folder": "street/3840/",
        "title": "S520-3840p-75",
        "description": "",
        "width": 3840,
        "height": 2560,
        "src": "https://media.publit.io/file/street/3840/S520-3840p-75.jpg"
      },
      {
        "id": "WSWoJyRD",
        "folder": "street/3840/",
        "title": "S513-3840p-75",
        "description": "",
        "width": 2560,
        "height": 3840,
        "src": "https://media.publit.io/file/street/3840/S513-3840p-75.jpg"
      },
      {
        "id": "2vXPG2TH",
        "folder": "street/3840/",
        "title": "S499-3840p-75",
        "description": "",
        "width": 3840,
        "height": 2560,
        "src": "https://media.publit.io/file/street/3840/S499-3840p-75.jpg"
      },
      {
        "id": "9mZxoPB0",
        "folder": "street/3840/",
        "title": "S456-3840p-75",
        "description": "",
        "width": 2560,
        "height": 3840,
        "src": "https://media.publit.io/file/street/3840/S456-3840p-75.jpg"
      },
      {
        "id": "58jfagJD",
        "folder": "street/3840/",
        "title": "S370-3840p-75",
        "description": "",
        "width": 2560,
        "height": 3840,
        "src": "https://media.publit.io/file/street/3840/S370-3840p-75.jpg"
      },
      {
        "id": "h2d8q4lq",
        "folder": "street/3840/",
        "title": "S367-3840p-75",
        "description": "",
        "width": 2880,
        "height": 3840,
        "src": "https://media.publit.io/file/street/3840/S367-3840p-75.jpg"
      },
      {
        "id": "Lx2xxGNQ",
        "folder": "street/3840/",
        "title": "S325-3840p-75",
        "description": "",
        "width": 2880,
        "height": 3840,
        "src": "https://media.publit.io/file/street/3840/S325-3840p-75.jpg"
      },
      {
        "id": "RMw6Wcvi",
        "folder": "street/3840/",
        "title": "S311-3840p-75",
        "description": "",
        "width": 3840,
        "height": 2560,
        "src": "https://media.publit.io/file/street/3840/S311-3840p-75.jpg"
      },
      {
        "id": "tzyWSpqs",
        "folder": "street/3840/",
        "title": "S310-3840p-75",
        "description": "",
        "width": 3840,
        "height": 2880,
        "src": "https://media.publit.io/file/street/3840/S310-3840p-75.jpg"
      },
      {
        "id": "RRb6DaPh",
        "folder": "street/3840/",
        "title": "S309-3840p-75",
        "description": "",
        "width": 3840,
        "height": 2560,
        "src": "https://media.publit.io/file/street/3840/S309-3840p-75.jpg"
      },
      {
        "id": "2hxbp1qi",
        "folder": "street/3840/",
        "title": "S219-3840p-75",
        "description": "",
        "width": 3840,
        "height": 2880,
        "src": "https://media.publit.io/file/street/3840/S219-3840p-75.jpg"
      },
      {
        "id": "qiJyV1WJ",
        "folder": "street/3840/",
        "title": "S185-3840p-75",
        "description": "",
        "width": 3840,
        "height": 2560,
        "src": "https://media.publit.io/file/street/3840/S185-3840p-75.jpg"
      },
      {
        "id": "me8PotcP",
        "folder": "street/3840/",
        "title": "S184-3840p-75",
        "description": "",
        "width": 3840,
        "height": 2880,
        "src": "https://media.publit.io/file/street/3840/S184-3840p-75.jpg"
      },
      {
        "id": "Jm3xhmJB",
        "folder": "street/3840/",
        "title": "S177-3840p-75",
        "description": "",
        "width": 3840,
        "height": 2880,
        "src": "https://media.publit.io/file/street/3840/S177-3840p-75.jpg"
      },
      {
        "id": "emzcJnSX",
        "folder": "street/3840/",
        "title": "S129-3840p-75",
        "description": "",
        "width": 3840,
        "height": 2560,
        "src": "https://media.publit.io/file/street/3840/S129-3840p-75.jpg"
      },
      {
        "id": "TkVxRGfr",
        "folder": "street/3840/",
        "title": "S119-3840p-75",
        "description": "",
        "width": 3840,
        "height": 2880,
        "src": "https://media.publit.io/file/street/3840/S119-3840p-75.jpg"
      },
      {
        "id": "AVRgZzL9",
        "folder": "street/3840/",
        "title": "S087-3840p-75",
        "description": "",
        "width": 3840,
        "height": 2880,
        "src": "https://media.publit.io/file/street/3840/S087-3840p-75.jpg"
      },
      {
        "id": "PaLGZTDH",
        "folder": "street/3840/",
        "title": "S060-3840p-75",
        "description": "",
        "width": 3840,
        "height": 2880,
        "src": "https://media.publit.io/file/street/3840/S060-3840p-75.jpg"
      },
      {
        "id": "fHbQvwto",
        "folder": "street/3840/",
        "title": "S051-3840p-75",
        "description": "",
        "width": 2880,
        "height": 3840,
        "src": "https://media.publit.io/file/street/3840/S051-3840p-75.jpg"
      },
      {
        "id": "GgN9uM5H",
        "folder": "street/3840/",
        "title": "S016-3840p-75",
        "description": "",
        "width": 2880,
        "height": 3840,
        "src": "https://media.publit.io/file/street/3840/S016-3840p-75.jpg"
      },
      {
        "id": "6tRbsqsJ",
        "folder": "street/3840/",
        "title": "S006-3840p-75",
        "description": "",
        "width": 3840,
        "height": 2560,
        "src": "https://media.publit.io/file/street/3840/S006-3840p-75.jpg"
      }
    ],
    "portraits": [
      {
        "id": "xnwprZiV",
        "folder": "portraits/3840/",
        "title": "P996-3840p-75",
        "description": "",
        "width": 2880,
        "height": 3840,
        "src": "https://media.publit.io/file/portraits/3840/P996-3840p-75.jpg"
      },
      {
        "id": "QJorHJs8",
        "folder": "portraits/3840/",
        "title": "P922-3840p-75",
        "description": "",
        "width": 3840,
        "height": 2880,
        "src": "https://media.publit.io/file/portraits/3840/P922-3840p-75.jpg"
      },
      {
        "id": "osVtWw7N",
        "folder": "portraits/3840/",
        "title": "P814-3840p-75",
        "description": "",
        "width": 2880,
        "height": 3840,
        "src": "https://media.publit.io/file/portraits/3840/P814-3840p-75.jpg"
      },
      {
        "id": "fM10H3fA",
        "folder": "portraits/3840/",
        "title": "P798-3840p-75",
        "description": "",
        "width": 2880,
        "height": 3840,
        "src": "https://media.publit.io/file/portraits/3840/P798-3840p-75.jpg"
      },
      {
        "id": "XZsl56Wt",
        "folder": "portraits/3840/",
        "title": "P744-3840p-75",
        "description": "",
        "width": 3840,
        "height": 2880,
        "src": "https://media.publit.io/file/portraits/3840/P744-3840p-75.jpg"
      },
      {
        "id": "VJsN9vQ5",
        "folder": "portraits/3840/",
        "title": "P714-3840p-75",
        "description": "",
        "width": 3072,
        "height": 3840,
        "src": "https://media.publit.io/file/portraits/3840/P714-3840p-75.jpg"
      },
      {
        "id": "cPnG1yuz",
        "folder": "portraits/3840/",
        "title": "P708-3840p-75",
        "description": "",
        "width": 3840,
        "height": 2880,
        "src": "https://media.publit.io/file/portraits/3840/P708-3840p-75.jpg"
      },
      {
        "id": "TTvj8ua5",
        "folder": "portraits/3840/",
        "title": "P707-3840p-75",
        "description": "",
        "width": 3840,
        "height": 2880,
        "src": "https://media.publit.io/file/portraits/3840/P707-3840p-75.jpg"
      },
      {
        "id": "GykPcpAk",
        "folder": "portraits/3840/",
        "title": "P706-3840p-75",
        "description": "",
        "width": 3840,
        "height": 2880,
        "src": "https://media.publit.io/file/portraits/3840/P706-3840p-75.jpg"
      },
      {
        "id": "d1TRasJa",
        "folder": "portraits/3840/",
        "title": "P691-3840p-75",
        "description": "",
        "width": 2880,
        "height": 3840,
        "src": "https://media.publit.io/file/portraits/3840/P691-3840p-75.jpg"
      },
      {
        "id": "pqsipbRG",
        "folder": "portraits/3840/",
        "title": "P649-3840p-75",
        "description": "",
        "width": 3840,
        "height": 2880,
        "src": "https://media.publit.io/file/portraits/3840/P649-3840p-75.jpg"
      },
      {
        "id": "cwS2XeAs",
        "folder": "portraits/3840/",
        "title": "P638-3840p-75",
        "description": "",
        "width": 2536,
        "height": 1691,
        "src": "https://media.publit.io/file/portraits/3840/P638-3840p-75.jpg"
      },
      {
        "id": "cJ6ff9ox",
        "folder": "portraits/3840/",
        "title": "P580-3840p-75",
        "description": "",
        "width": 3840,
        "height": 2880,
        "src": "https://media.publit.io/file/portraits/3840/P580-3840p-75.jpg"
      },
      {
        "id": "fLz76eD1",
        "folder": "portraits/3840/",
        "title": "P532-Edit-3840p-75",
        "description": "",
        "width": 3840,
        "height": 2880,
        "src": "https://media.publit.io/file/portraits/3840/P532-Edit-3840p-75.jpg"
      },
      {
        "id": "eH3fJB94",
        "folder": "portraits/3840/",
        "title": "P532-3840p-75",
        "description": "",
        "width": 3840,
        "height": 2880,
        "src": "https://media.publit.io/file/portraits/3840/P532-3840p-75.jpg"
      },
      {
        "id": "kimplH0R",
        "folder": "portraits/3840/",
        "title": "P514-3840p-75",
        "description": "",
        "width": 3840,
        "height": 2880,
        "src": "https://media.publit.io/file/portraits/3840/P514-3840p-75.jpg"
      },
      {
        "id": "5iW3R2Pg",
        "folder": "portraits/3840/",
        "title": "P479-3840p-75",
        "description": "",
        "width": 3840,
        "height": 2560,
        "src": "https://media.publit.io/file/portraits/3840/P479-3840p-75.jpg"
      },
      {
        "id": "qlJX2u51",
        "folder": "portraits/3840/",
        "title": "P442-3840p-75",
        "description": "",
        "width": 3840,
        "height": 2560,
        "src": "https://media.publit.io/file/portraits/3840/P442-3840p-75.jpg"
      },
      {
        "id": "AgXh7S5H",
        "folder": "portraits/3840/",
        "title": "P367-3840p-75",
        "description": "",
        "width": 2880,
        "height": 3840,
        "src": "https://media.publit.io/file/portraits/3840/P367-3840p-75.jpg"
      },
      {
        "id": "egnpAJPr",
        "folder": "portraits/3840/",
        "title": "P340-3840p-75",
        "description": "",
        "width": 2880,
        "height": 3840,
        "src": "https://media.publit.io/file/portraits/3840/P340-3840p-75.jpg"
      },
      {
        "id": "NX8HoHRc",
        "folder": "portraits/3840/",
        "title": "P336-3840p-75",
        "description": "",
        "width": 2560,
        "height": 3840,
        "src": "https://media.publit.io/file/portraits/3840/P336-3840p-75.jpg"
      },
      {
        "id": "P5gzfNZR",
        "folder": "portraits/3840/",
        "title": "P322-3840p-75",
        "description": "",
        "width": 2880,
        "height": 3840,
        "src": "https://media.publit.io/file/portraits/3840/P322-3840p-75.jpg"
      },
      {
        "id": "NzWDPHAl",
        "folder": "portraits/3840/",
        "title": "P314-3840p-75",
        "description": "",
        "width": 2880,
        "height": 3840,
        "src": "https://media.publit.io/file/portraits/3840/P314-3840p-75.jpg"
      },
      {
        "id": "Hx0MTHfA",
        "folder": "portraits/3840/",
        "title": "P308-3840p-75",
        "description": "",
        "width": 2560,
        "height": 3840,
        "src": "https://media.publit.io/file/portraits/3840/P308-3840p-75.jpg"
      },
      {
        "id": "dhpv4nv9",
        "folder": "portraits/3840/",
        "title": "P303-3840p-75",
        "description": "",
        "width": 3840,
        "height": 2880,
        "src": "https://media.publit.io/file/portraits/3840/P303-3840p-75.jpg"
      },
      {
        "id": "oQ0HV8eL",
        "folder": "portraits/3840/",
        "title": "P227-3840p-75",
        "description": "",
        "width": 3840,
        "height": 2880,
        "src": "https://media.publit.io/file/portraits/3840/P227-3840p-75.jpg"
      },
      {
        "id": "5tMSPNQ5",
        "folder": "portraits/3840/",
        "title": "P216-3840p-75",
        "description": "",
        "width": 3840,
        "height": 2880,
        "src": "https://media.publit.io/file/portraits/3840/P216-3840p-75.jpg"
      },
      {
        "id": "8cQxy3sD",
        "folder": "portraits/3840/",
        "title": "P214-3840p-75",
        "description": "",
        "width": 2880,
        "height": 3840,
        "src": "https://media.publit.io/file/portraits/3840/P214-3840p-75.jpg"
      },
      {
        "id": "vrocXfci",
        "folder": "portraits/3840/",
        "title": "P201-3840p-75",
        "description": "",
        "width": 3840,
        "height": 2560,
        "src": "https://media.publit.io/file/portraits/3840/P201-3840p-75.jpg"
      },
      {
        "id": "ww5D4sgg",
        "folder": "portraits/3840/",
        "title": "P199-3840p-75",
        "description": "",
        "width": 3840,
        "height": 2880,
        "src": "https://media.publit.io/file/portraits/3840/P199-3840p-75.jpg"
      },
      {
        "id": "MrjS0ndW",
        "folder": "portraits/3840/",
        "title": "P155-3840p-75",
        "description": "",
        "width": 2880,
        "height": 3840,
        "src": "https://media.publit.io/file/portraits/3840/P155-3840p-75.jpg"
      },
      {
        "id": "ecb2oG7i",
        "folder": "portraits/3840/",
        "title": "P149-3840p-75",
        "description": "",
        "width": 3840,
        "height": 2880,
        "src": "https://media.publit.io/file/portraits/3840/P149-3840p-75.jpg"
      },
      {
        "id": "V2keLy8B",
        "folder": "portraits/3840/",
        "title": "P119-3840p-75",
        "description": "",
        "width": 3840,
        "height": 2560,
        "src": "https://media.publit.io/file/portraits/3840/P119-3840p-75.jpg"
      },
      {
        "id": "brj7nTTA",
        "folder": "portraits/3840/",
        "title": "P081-3840p-75",
        "description": "",
        "width": 3840,
        "height": 2880,
        "src": "https://media.publit.io/file/portraits/3840/P081-3840p-75.jpg"
      }
    ],
    "landscape": [
      {
        "id": "Q3yla8xu",
        "folder": "landscape/3840/",
        "title": "L994-3840p-75",
        "description": "",
        "width": 3840,
        "height": 2560,
        "src": "https://media.publit.io/file/landscape/3840/L994-3840p-75.jpg"
      },
      {
        "id": "TnaNbdbS",
        "folder": "landscape/3840/",
        "title": "L912-3840p-75",
        "description": "",
        "width": 3840,
        "height": 2560,
        "src": "https://media.publit.io/file/landscape/3840/L912-3840p-75.jpg"
      },
      {
        "id": "867Dpl0b",
        "folder": "landscape/3840/",
        "title": "L896-3840p-75",
        "description": "",
        "width": 2880,
        "height": 3840,
        "src": "https://media.publit.io/file/landscape/3840/L896-3840p-75.jpg"
      },
      {
        "id": "SBsXLvl0",
        "folder": "landscape/3840/",
        "title": "L889-3840p-75",
        "description": "",
        "width": 2560,
        "height": 3840,
        "src": "https://media.publit.io/file/landscape/3840/L889-3840p-75.jpg"
      },
      {
        "id": "gdkg8sJ3",
        "folder": "landscape/3840/",
        "title": "L887-3840p-75",
        "description": "",
        "width": 3840,
        "height": 2560,
        "src": "https://media.publit.io/file/landscape/3840/L887-3840p-75.jpg"
      },
      {
        "id": "zq0ZdB1j",
        "folder": "landscape/3840/",
        "title": "L874-Pano-3840p-75",
        "description": "",
        "width": 3840,
        "height": 1253,
        "src": "https://media.publit.io/file/landscape/3840/L874-Pano-3840p-75.jpg"
      },
      {
        "id": "fueei7XH",
        "folder": "landscape/3840/",
        "title": "L800-3840p-75",
        "description": "",
        "width": 3840,
        "height": 2560,
        "src": "https://media.publit.io/file/landscape/3840/L800-3840p-75.jpg"
      },
      {
        "id": "HTBm36X3",
        "folder": "landscape/3840/",
        "title": "L787-3840p-75",
        "description": "",
        "width": 3840,
        "height": 2880,
        "src": "https://media.publit.io/file/landscape/3840/L787-3840p-75.jpg"
      },
      {
        "id": "jxZXMXzb",
        "folder": "landscape/3840/",
        "title": "L700-3840p-75",
        "description": "",
        "width": 3840,
        "height": 2880,
        "src": "https://media.publit.io/file/landscape/3840/L700-3840p-75.jpg"
      },
      {
        "id": "JWAvf4jv",
        "folder": "landscape/3840/",
        "title": "L698-3840p-75",
        "description": "",
        "width": 3840,
        "height": 2880,
        "src": "https://media.publit.io/file/landscape/3840/L698-3840p-75.jpg"
      },
      {
        "id": "gmdhqvNP",
        "folder": "landscape/3840/",
        "title": "L694-3840p-75",
        "description": "",
        "width": 3840,
        "height": 2560,
        "src": "https://media.publit.io/file/landscape/3840/L694-3840p-75.jpg"
      },
      {
        "id": "3T6xxJou",
        "folder": "landscape/3840/",
        "title": "L682-3840p-75",
        "description": "",
        "width": 2560,
        "height": 3840,
        "src": "https://media.publit.io/file/landscape/3840/L682-3840p-75.jpg"
      },
      {
        "id": "8ptPumdt",
        "folder": "landscape/3840/",
        "title": "L628-Pano-3840p-75",
        "description": "",
        "width": 3840,
        "height": 1743,
        "src": "https://media.publit.io/file/landscape/3840/L628-Pano-3840p-75.jpg"
      },
      {
        "id": "9APqizxa",
        "folder": "landscape/3840/",
        "title": "L537-3840p-75",
        "description": "",
        "width": 3840,
        "height": 2560,
        "src": "https://media.publit.io/file/landscape/3840/L537-3840p-75.jpg"
      },
      {
        "id": "x5fAgZ2g",
        "folder": "landscape/3840/",
        "title": "L525-Pano-3840p-75",
        "description": "",
        "width": 3840,
        "height": 1033,
        "src": "https://media.publit.io/file/landscape/3840/L525-Pano-3840p-75.jpg"
      },
      {
        "id": "PL1ptQu6",
        "folder": "landscape/3840/",
        "title": "L517-3840p-75",
        "description": "",
        "width": 3840,
        "height": 2880,
        "src": "https://media.publit.io/file/landscape/3840/L517-3840p-75.jpg"
      },
      {
        "id": "uiGAlRAL",
        "folder": "landscape/3840/",
        "title": "L487-Pano-3840p-75",
        "description": "",
        "width": 3840,
        "height": 1300,
        "src": "https://media.publit.io/file/landscape/3840/L487-Pano-3840p-75.jpg"
      },
      {
        "id": "mZxnD4zn",
        "folder": "landscape/3840/",
        "title": "L486-3840p-75",
        "description": "",
        "width": 3840,
        "height": 2560,
        "src": "https://media.publit.io/file/landscape/3840/L486-3840p-75.jpg"
      },
      {
        "id": "14f85AVd",
        "folder": "landscape/3840/",
        "title": "L413-3840p-75",
        "description": "",
        "width": 3840,
        "height": 2880,
        "src": "https://media.publit.io/file/landscape/3840/L413-3840p-75.jpg"
      },
      {
        "id": "cliLNkG0",
        "folder": "landscape/3840/",
        "title": "L287-3840p-75",
        "description": "",
        "width": 2880,
        "height": 3840,
        "src": "https://media.publit.io/file/landscape/3840/L287-3840p-75.jpg"
      },
      {
        "id": "Arahbqpd",
        "folder": "landscape/3840/",
        "title": "L281-3840p-75",
        "description": "",
        "width": 3072,
        "height": 3840,
        "src": "https://media.publit.io/file/landscape/3840/L281-3840p-75.jpg"
      },
      {
        "id": "XTuRntpw",
        "folder": "landscape/3840/",
        "title": "L169-3840p-75",
        "description": "",
        "width": 2880,
        "height": 3840,
        "src": "https://media.publit.io/file/landscape/3840/L169-3840p-75.jpg"
      },
      {
        "id": "9bZpq8kj",
        "folder": "landscape/3840/",
        "title": "L154-3840p-75",
        "description": "",
        "width": 2880,
        "height": 3840,
        "src": "https://media.publit.io/file/landscape/3840/L154-3840p-75.jpg"
      },
      {
        "id": "TV9gvprm",
        "folder": "landscape/3840/",
        "title": "L113-3840p-75",
        "description": "",
        "width": 2560,
        "height": 3840,
        "src": "https://media.publit.io/file/landscape/3840/L113-3840p-75.jpg"
      },
      {
        "id": "LhhMdWGS",
        "folder": "landscape/3840/",
        "title": "L103-3840p-75",
        "description": "",
        "width": 2880,
        "height": 3840,
        "src": "https://media.publit.io/file/landscape/3840/L103-3840p-75.jpg"
      },
      {
        "id": "3RHzwehH",
        "folder": "landscape/3840/",
        "title": "L086-3840p-75",
        "description": "",
        "width": 3840,
        "height": 2560,
        "src": "https://media.publit.io/file/landscape/3840/L086-3840p-75.jpg"
      },
      {
        "id": "dcdJxczG",
        "folder": "landscape/3840/",
        "title": "L033-3840p-75",
        "description": "",
        "width": 3840,
        "height": 2880,
        "src": "https://media.publit.io/file/landscape/3840/L033-3840p-75.jpg"
      },
      {
        "id": "LPS0RWN3",
        "folder": "landscape/3840/",
        "title": "L001-3840p-75",
        "description": "",
        "width": 2880,
        "height": 3840,
        "src": "https://media.publit.io/file/landscape/3840/L001-3840p-75.jpg"
      }
    ]
  }
}
